anibridge_plex_provider/__init__.py
anibridge_plex_provider/client.py
anibridge_plex_provider/community.py
anibridge_plex_provider/library.py
anibridge_plex_provider/utils.py
anibridge_plex_provider/webhook.py
anibridge_plex_provider-0.1.2.dist-info/WHEEL
anibridge_plex_provider-0.1.2.dist-info/METADATA
anibridge_plex_provider-0.1.2.dist-info/RECORD
